sqlmodel_serializers/__init__.py
sqlmodel_serializers/base.py
sqlmodel_serializers/filters.py
sqlmodel_serializers/meta.py
sqlmodel_serializers/serializers.py
sqlmodel_serializers/types.py
sqlmodel_serializers-0.0.2.dist-info/LICENSE
sqlmodel_serializers-0.0.2.dist-info/METADATA
sqlmodel_serializers-0.0.2.dist-info/WHEEL
sqlmodel_serializers-0.0.2.dist-info/top_level.txt
sqlmodel_serializers-0.0.2.dist-info/RECORD
