Metadata-Version: 2.1
Name: sqlmodel-serializers
Version: 0.0.2
Summary: Model serializer for SQLModel
Home-page: https://notabug.org/kapustlo/sqlmodel-serializers
Author: Kapustlo
Keywords: python,sqlmodel,pydantic,sqlalchemy,orm,serializer
Classifier: License :: OSI Approved :: MIT License
Classifier: Topic :: Software Development :: Libraries :: Python Modules
Classifier: Development Status :: 3 - Alpha
Classifier: Intended Audience :: Developers
Classifier: Programming Language :: Python :: 3.9
Classifier: Operating System :: OS Independent
Classifier: Natural Language :: English
Requires-Python: >=3.9
License-File: LICENSE
Requires-Dist: sqlmodel
